shcmder/__init__.py
shcmder/shcmder.py
shcmder-0.0.5.dist-info/METADATA
shcmder-0.0.5.dist-info/WHEEL
shcmder-0.0.5.dist-info/licenses/LICENSE
shcmder-0.0.5.dist-info/RECORD
